{
    "pools": [
      {
        "rolls": 1,
        "entries": [
          {
            "type": "minecraft:item",
            "name": "paper",
            "functions": [
              {
                "function": "minecraft:set_components",
                "components": {
                  "minecraft:custom_data": "{pc:{item_name:{text:'Fading Compass'},category:'skill',item:'fading_compass',tip:{shield:true},durability:6,energy:2,rc:true,game_item:true}}",
                  "minecraft:item_model": "minecraft:recovery_compass","minecraft:max_stack_size": 1,"minecraft:consumable": {"consume_seconds": 94879487},
                  "minecraft:lore": [
                    [{"text": "", "italic": false},{"text":">>","color": "gray"},{"text":"> ","color": "#72bd7a","bold": true},{"text":"Ability","color": "#f5b055","bold": true}],
                    [{"text": "", "italic": false, "color": "white"}, {"text": "Deal 5 damage to all enemies within"}],
                    [{"text": "", "italic": false, "color": "white"}, {"text": "1 block or 1 diagonal block. Deals"}],
                    [{"text": "", "italic": false, "color": "white"}, {"text": "2 additional damage for remaining"}],
                    [{"text": "", "italic": false, "color": "white"}, {"text": "Durability", "color": "#f1de61"}, {"font": "pc:default", "text": "1", "color": "white"}, {"text": " of this item."}],
                    "",
                    [{"text": "", "italic": false, "color": "gray"}, {"text": "End of your turn:"}],
                    [{"text": "", "italic": false, "color": "white"}, {"text": "Gain (the remaining "}, {"text": "Durability", "color": "#f1de61"}, {"font": "pc:default", "text": "1", "color": "white"}],
                    [{"text": "", "italic": false, "color": "white"}, {"text": "of this item) "}, {"text": "Shield", "color": "#7abff1"}, {"text": "."}],
                    [{"text": "", "italic": false, "color": "white"}, {"text": "Consume 1 "}, {"text": "Durability", "color": "#f1de61"}, {"font": "pc:default", "text": "1", "color": "white"}, {"text": "."}],
                    "",
                    [{"text": "","italic": false},{"text":">>","color": "gray"},{"text":"> ","color": "#72bd7a","bold": true},{"text":"Details","color": "#3fa0e1","bold": true}],
                    [{"text": "","italic": false,"color": "gray"},{"text":"● ","color":"#72bd7a"},{"text":"ᴅᴜʀᴀʙɪʟɪᴛʏ : 6"},{"font":"pc:default","text":"1","color":"white"}],
                    [{"text": "","italic": false,"color": "gray"},{"text":"● ","color":"#72bd7a"},{"text":"ᴄᴀᴛᴇɢᴏʀʏ : ꜱᴋɪʟʟ"}]
                  ]
                }
              }
            ]
          }
        ]
      }
    ]
}